sproc/__init__.py
sproc/py.typed
sproc-2.4.1.dist-info/LICENSE
sproc-2.4.1.dist-info/METADATA
sproc-2.4.1.dist-info/WHEEL
sproc-2.4.1.dist-info/RECORD
