Metadata-Version: 2.1
Name: sproc
Version: 2.4.1
Summary: ⛏ Subprocesseses for subhumanses ⛏
Home-page: https://github.com/rec/sproc
License: MIT
Author: Tom Ritchford
Author-email: tom@swirly.com
Requires-Python: >=3.8
Classifier: License :: OSI Approved :: MIT License
Classifier: Programming Language :: Python :: 3
Classifier: Programming Language :: Python :: 3.8
Classifier: Programming Language :: Python :: 3.9
Classifier: Programming Language :: Python :: 3.10
Classifier: Programming Language :: Python :: 3.11
Classifier: Programming Language :: Python :: 3.12
Project-URL: Documentation, https://rec.github.io/sproc
Project-URL: Repository, https://github.com/rec/sproc
